gradio_motioncanvasplayer/__init__.py
gradio_motioncanvasplayer/motioncanvasplayer.py
gradio_motioncanvasplayer/motioncanvasplayer.pyi
gradio_motioncanvasplayer/templates/component/index.js
gradio_motioncanvasplayer/templates/component/style.css
gradio_motioncanvasplayer/templates/example/index.js
gradio_motioncanvasplayer/templates/example/style.css
gradio_motioncanvasplayer-0.0.2.dist-info/METADATA
gradio_motioncanvasplayer-0.0.2.dist-info/WHEEL
gradio_motioncanvasplayer-0.0.2.dist-info/RECORD
