Metadata-Version: 2.4
Name: gradio_motioncanvasplayer
Version: 0.0.2
Summary: This custom component for Gradio displays Motion Canvas projects in the browser. Motion Canvas is a library for generating animations, videos, or presentations via the Canvas API. All animations are defined by code - an excellent playground for AI agents. An exemplary demo for this component is available in this Huggingface Space: https://huggingface.co/spaces/prathje/gradio_motioncanvasplayer. The source code for the included project can be found at: https://github.com/prathje/gradio-m
Project-URL: repository, https://github.com/prathje/gradio-motioncanvasplayer
Project-URL: space, https://huggingface.co/spaces/prathje/gradio_motioncanvasplayer
Author-email: Patrick Rathje <info@patrickrathje.de>
License-Expression: MIT
Keywords: Animation,Motion Canvas,Player,gradio-custom-component,gradio-template-HTML
Classifier: Development Status :: 3 - Alpha
Classifier: Operating System :: OS Independent
Classifier: Programming Language :: Python :: 3
Classifier: Programming Language :: Python :: 3 :: Only
Classifier: Programming Language :: Python :: 3.8
Classifier: Programming Language :: Python :: 3.9
Classifier: Programming Language :: Python :: 3.10
Classifier: Programming Language :: Python :: 3.11
Classifier: Topic :: Scientific/Engineering
Classifier: Topic :: Scientific/Engineering :: Artificial Intelligence
Classifier: Topic :: Scientific/Engineering :: Visualization
Requires-Python: >=3.10
Requires-Dist: gradio<6.0,>=4.0
Provides-Extra: dev
Requires-Dist: build; extra == 'dev'
Requires-Dist: twine; extra == 'dev'
